jcclass/__init__.py
jcclass/compute/__init__.py
jcclass/compute/core.py
jcclass/compute/functions/__init__.py
jcclass/compute/functions/computation.py
jcclass/compute/functions/constants.py
jcclass/compute/functions/data_extraction.py
jcclass/compute/functions/data_preparation.py
jcclass/compute/functions/format_data.py
jcclass/compute/functions/main.py
jcclass/plotting/__init__.py
jcclass/plotting/core.py
jcclass/plotting/functions/__init__.py
jcclass/plotting/functions/plot_utils.py
jcclass/plotting/functions/tools.py
jcclass/utils/__init__.py
jcclass/utils/logging_config.py
jcclass-0.0.9.dist-info/METADATA
jcclass-0.0.9.dist-info/WHEEL
jcclass-0.0.9.dist-info/top_level.txt
jcclass-0.0.9.dist-info/RECORD
